ssloop3/__init__.py
ssloop3/event.py
ssloop3/loop.py
ssloop3/net.py
ssloop3/impl/__init__.py
ssloop3/impl/epoll_loop.py
ssloop3/impl/kqueue_loop.py
ssloop3/impl/select_loop.py
ssloop3-0.0.1.dist-info/METADATA
ssloop3-0.0.1.dist-info/WHEEL
ssloop3-0.0.1.dist-info/top_level.txt
ssloop3-0.0.1.dist-info/RECORD
