Metadata-Version: 2.1
Name: ssloop3
Version: 0.0.1
Summary: super lightweight event loop
Home-page: http://github.com/mtclinton/ssloop3
Author: mtclinton
Author-email: max@mtclinton.com
License: MIT
Platform: UNKNOWN
